tests/test_sync_retry.py
tests/test_con_utils.py
tests/test_async_tx.py
tests/test_postgis.py
tests/test_connect.py
tests/test_errors.py
tests/test_scram.py
tests/bench_uuid.py
tests/test_async_retry.py
tests/__init__.py
tests/test_proto.py
tests/test_asyncio_client.py
tests/test_globals.py
tests/test_credentials.py
tests/test_state.py
tests/test_datetime.py
tests/test_sync_tx.py
tests/test_namedtuples.py
tests/test_vector.py
tests/test_sourcecode.py
tests/test_sync_query.py
tests/test_memory.py
tests/test_async_query.py
tests/test_blocking_client.py
tests/credentials1.json
tests/test_codegen.py
tests/test_enum.py
tests/datatypes/test_datatypes.py
tests/datatypes/__init__.py
tests/datatypes/test_uuid.py
tests/shared-client-testcases/connection_testcases.json
tests/shared-client-testcases/project_path_hashing_testcases.json
edgedb/abstract.py
edgedb/options.py
edgedb/describe.py
edgedb/enums.py
edgedb/color.py
edgedb/_version.py
edgedb/credentials.py
edgedb/transaction.py
edgedb/base_client.py
edgedb/_testbase.py
edgedb/__init__.py
edgedb/introspect.py
edgedb/blocking_client.py
edgedb/platform.py
edgedb/asyncio_client.py
edgedb/con_utils.py
edgedb/py.typed
edgedb/connresource.py
edgedb/_taskgroup.py
edgedb/datatypes/comp.c
edgedb/datatypes/namedtuple.c
edgedb/datatypes/freelist.h
edgedb/datatypes/args.c
edgedb/datatypes/internal.h
edgedb/datatypes/datatypes.c
edgedb/datatypes/object.c
edgedb/datatypes/config_memory.pyx
edgedb/datatypes/relative_duration.pxd
edgedb/datatypes/link.c
edgedb/datatypes/datatypes.cpython-310-darwin.so
edgedb/datatypes/__init__.pxd
edgedb/datatypes/linkset.c
edgedb/datatypes/date_duration.pyx
edgedb/datatypes/range.py
edgedb/datatypes/pythoncapi_compat.h
edgedb/datatypes/datatypes.pxd
edgedb/datatypes/__init__.py
edgedb/datatypes/hash.c
edgedb/datatypes/enum.pyx
edgedb/datatypes/datatypes.h
edgedb/datatypes/record_desc.c
edgedb/datatypes/datatypes.pyx
edgedb-2.2.0.dist-info/RECORD
edgedb-2.2.0.dist-info/LICENSE
edgedb-2.2.0.dist-info/WHEEL
edgedb-2.2.0.dist-info/entry_points.txt
edgedb-2.2.0.dist-info/top_level.txt
edgedb-2.2.0.dist-info/METADATA
