Metadata-Version: 2.1
Name: edgedb
Version: 2.2.0
Summary: EdgeDB Python driver
Home-page: https://github.com/edgedb/edgedb-python
Author: MagicStack Inc
Author-email: hello@magic.io
License: Apache License, Version 2.0
Platform: macOS
Platform: POSIX
Platform: Windows
Provides: edgedb
Requires-Python: >=3.8
License-File: LICENSE
Requires-Dist: certifi>=2021.5.30; platform_system == "Windows"
Provides-Extra: ai
Requires-Dist: httpx~=0.27.0; extra == "ai"
Requires-Dist: httpx-sse~=0.4.0; extra == "ai"
Provides-Extra: docs
Requires-Dist: sphinx~=4.2.0; extra == "docs"
Requires-Dist: sphinxcontrib-asyncio~=0.3.0; extra == "docs"
Requires-Dist: sphinx_rtd_theme~=1.0.0; extra == "docs"
Provides-Extra: test
Requires-Dist: pycodestyle~=2.11.1; extra == "test"
Requires-Dist: pyflakes~=3.2.0; extra == "test"
Requires-Dist: flake8-bugbear~=24.4.26; extra == "test"
Requires-Dist: flake8~=7.0.0; extra == "test"
Requires-Dist: uvloop>=0.15.1; platform_system != "Windows" and extra == "test"
Provides-Extra: dev
Requires-Dist: Cython<3.1.0,>=3.0.11; extra == "dev"
Requires-Dist: pytest>=3.6.0; extra == "dev"
Requires-Dist: sphinx~=4.2.0; extra == "dev"
Requires-Dist: sphinxcontrib-asyncio~=0.3.0; extra == "dev"
Requires-Dist: sphinx_rtd_theme~=1.0.0; extra == "dev"
Requires-Dist: pycodestyle~=2.11.1; extra == "dev"
Requires-Dist: pyflakes~=3.2.0; extra == "dev"
Requires-Dist: flake8-bugbear~=24.4.26; extra == "dev"
Requires-Dist: flake8~=7.0.0; extra == "dev"
Requires-Dist: uvloop>=0.15.1; platform_system != "Windows" and extra == "dev"
